django_po_translate-1.15.dist-info/licenses/LICENSE
po_translate/__init__.py
po_translate/admin.py
po_translate/apps.py
po_translate/models.py
po_translate/tests.py
po_translate/views.py
po_translate/management/__init__.py
po_translate/management/commands/__init__.py
po_translate/management/commands/makemessages.py
po_translate/migrations/__init__.py
django_po_translate-1.15.dist-info/METADATA
django_po_translate-1.15.dist-info/WHEEL
django_po_translate-1.15.dist-info/top_level.txt
django_po_translate-1.15.dist-info/RECORD
