Metadata-Version: 2.4
Name: django-po-translate
Version: 1.15
Summary: Django app with updated makemessages command to add automatic translation.
Home-page: https://github.com/KokocGroup/django-po-translate
Author: KokocGroup
Author-email: dev@kokoc.com
License: BSD
Classifier: Environment :: Web Environment
Classifier: Framework :: Django
Classifier: Intended Audience :: Developers
Classifier: License :: OSI Approved :: BSD License
Classifier: Operating System :: OS Independent
Classifier: Programming Language :: Python
Classifier: Programming Language :: Python :: 3
Classifier: Programming Language :: Python :: 3 :: Only
Classifier: Programming Language :: Python :: 3.6
Classifier: Topic :: Internet :: WWW/HTTP
Requires-Python: >=3.6
License-File: LICENSE
Requires-Dist: polib>=1.1.1
Requires-Dist: googletrans>=4.0.2
Dynamic: license-file
